llamppl/__init__.py
llamppl/chunks.py
llamppl/llms.py
llamppl/modeling.py
llamppl/util.py
llamppl/distributions/__init__.py
llamppl/distributions/bernoulli.py
llamppl/distributions/distribution.py
llamppl/distributions/geometric.py
llamppl/distributions/lmcontext.py
llamppl/distributions/logcategorical.py
llamppl/distributions/tokencategorical.py
llamppl/distributions/transformer.py
llamppl/inference/__init__.py
llamppl/inference/smc_record.py
llamppl/inference/smc_standard.py
llamppl/inference/smc_steer.py
llamppl-0.2.1.dist-info/licenses/LICENSE
llamppl-0.2.1.dist-info/METADATA
llamppl-0.2.1.dist-info/WHEEL
llamppl-0.2.1.dist-info/top_level.txt
llamppl-0.2.1.dist-info/RECORD
