Metadata-Version: 2.4
Name: llamppl
Version: 0.2.1
Summary: Probabilistic programming with Large Language Models.
Author-email: Alex Lew <alexlew@mit.edu>, Gabriel Grand <grandg@mit.edu>, Ben LeBrun <benlebrun1@gmail.com>
License: MIT
Requires-Python: >=3.10
License-File: LICENSE
Requires-Dist: torch>=2.1.2
Requires-Dist: numpy>=1.26.2
Requires-Dist: scipy>=1.11.4
Requires-Dist: protobuf>=5.27.2
Requires-Dist: pre-commit>=3.7.1
Requires-Dist: ipykernel>=6.29.5
Requires-Dist: genlm-backend>=0.1.0a1
Provides-Extra: vllm
Requires-Dist: vllm>=0.6.6; extra == "vllm"
Provides-Extra: dev
Requires-Dist: pytest; extra == "dev"
Requires-Dist: pytest-benchmark; extra == "dev"
Requires-Dist: pytest-cov; extra == "dev"
Requires-Dist: pre-commit>=3.6.0; extra == "dev"
Requires-Dist: ruff>=0.9.9; extra == "dev"
Requires-Dist: jupyterlab>=4.0.9; extra == "dev"
Requires-Dist: ipywidgets>=8.1.1; extra == "dev"
Requires-Dist: matplotlib>=3.9.1; extra == "dev"
Requires-Dist: seaborn>=0.13.2; extra == "dev"
Provides-Extra: yelp
Requires-Dist: yake>=0.4.8; extra == "yelp"
Requires-Dist: datasets>=2.20.0; extra == "yelp"
Provides-Extra: collie
Requires-Dist: collie-bench>=0.1.0; extra == "collie"
Requires-Dist: nltk>=3.8.1; extra == "collie"
Requires-Dist: dill>=0.3.8; extra == "collie"
Requires-Dist: evaluate>=0.4.2; extra == "collie"
Provides-Extra: examples
Requires-Dist: nltk>=3.8.1; extra == "examples"
Dynamic: license-file
